Metadata-Version: 1.0
Name: udsnd-distributions
Version: 0.1
Summary: Gaussian and Binomial distributions
Home-page: UNKNOWN
Author: Hannes Engelbrecht
Author-email: UNKNOWN
License: UNKNOWN
Platform: UNKNOWN
